<?xml version="1.0" encoding="UTF-8"?>
<metadata xml:lang="zh"><Esri><CreaDate>20230131</CreaDate><CreaTime>01393400</CreaTime><ArcGISFormat>1.0</ArcGISFormat><SyncOnce>TRUE</SyncOnce><DataProperties><lineage><Process ToolSource="c:\program files (x86)\arcgis\desktop10.6\ArcToolbox\Toolboxes\Data Management Tools.tbx\CalculateField" Date="20230131" Time="012846">CalculateField 2020年\2020年县级 year 2019 VB #</Process><Process ToolSource="e:\program files\arcgis\desktop\desktop10.6\ArcToolbox\Toolboxes\Data Management Tools.tbx\CalculateField" Date="20230203" Time="223256">CalculateField 2019年\2019年县 曾用名 "从化市" VB #</Process><Process ToolSource="e:\program files\arcgis\desktop\desktop10.6\ArcToolbox\Toolboxes\Data Management Tools.tbx\CalculateField" Date="20230203" Time="223301">CalculateField 2019年\2019年县 备注 "2013年撤销从化市，设立从化区" VB #</Process><Process ToolSource="e:\program files\arcgis\desktop\desktop10.6\ArcToolbox\Toolboxes\Data Management Tools.tbx\CalculateField" Date="20230203" Time="223638">CalculateField 2019年\2019年县 曾用名 "增城市" VB #</Process><Process ToolSource="e:\program files\arcgis\desktop\desktop10.6\ArcToolbox\Toolboxes\Data Management Tools.tbx\CalculateField" Date="20230203" Time="223643">CalculateField 2019年\2019年县 备注 "2013年撤销增城市，设立增城区" VB #</Process><Process ToolSource="e:\program files\arcgis\desktop\desktop10.6\ArcToolbox\Toolboxes\Data Management Tools.tbx\CalculateField" Date="20230203" Time="230018">CalculateField 2019年\2019年县 备注 "2013年萝岗区并入黄埔区" VB #</Process><Process ToolSource="e:\program files\arcgis\desktop\desktop10.6\ArcToolbox\Toolboxes\Data Management Tools.tbx\CalculateField" Date="20230203" Time="235842">CalculateField 2019年\2019年县 曾用名 "云安县" VB #</Process><Process ToolSource="e:\program files\arcgis\desktop\desktop10.6\ArcToolbox\Toolboxes\Data Management Tools.tbx\CalculateField" Date="20230203" Time="235847">CalculateField 2019年\2019年县 备注 "2013年撤销云安县，设立云安区" VB #</Process><Process ToolSource="e:\program files\arcgis\desktop\desktop10.6\ArcToolbox\Toolboxes\Data Management Tools.tbx\CalculateField" Date="20230204" Time="000843">CalculateField 2019年\2019年县 曾用名 "阳东县" VB #</Process><Process ToolSource="e:\program files\arcgis\desktop\desktop10.6\ArcToolbox\Toolboxes\Data Management Tools.tbx\CalculateField" Date="20230204" Time="000849">CalculateField 2019年\2019年县 备注 "2013年撤销阳东县，设立阳东区" VB #</Process><Process ToolSource="e:\program files\arcgis\desktop\desktop10.6\ArcToolbox\Toolboxes\Data Management Tools.tbx\CalculateField" Date="20230204" Time="010615">CalculateField 2019年\2019年县 备注 "撤销茂港区、电白县，新设电白区" VB #</Process><Process ToolSource="e:\program files\arcgis\desktop\desktop10.6\ArcToolbox\Toolboxes\Data Management Tools.tbx\CalculateField" Date="20230204" Time="015147">CalculateField 2019年\2019年县 曾用名 "文登市" VB #</Process><Process ToolSource="e:\program files\arcgis\desktop\desktop10.6\ArcToolbox\Toolboxes\Data Management Tools.tbx\CalculateField" Date="20230204" Time="015153">CalculateField 2019年\2019年县 备注 "2013年撤销文登市，新设文登市" VB #</Process><Process ToolSource="e:\program files\arcgis\desktop\desktop10.6\ArcToolbox\Toolboxes\Data Management Tools.tbx\CalculateField" Date="20230204" Time="225346">CalculateField 2019年\2019年县 曾用名 "沾化县" VB #</Process><Process ToolSource="e:\program files\arcgis\desktop\desktop10.6\ArcToolbox\Toolboxes\Data Management Tools.tbx\CalculateField" Date="20230204" Time="225352">CalculateField 2019年\2019年县 备注 "2013年撤销沾化县，设立沾化区" VB #</Process><Process ToolSource="e:\program files\arcgis\desktop\desktop10.6\ArcToolbox\Toolboxes\Data Management Tools.tbx\CalculateField" Date="20230204" Time="230242">CalculateField 2019年\2019年县 曾用名 "陵县" VB #</Process><Process ToolSource="e:\program files\arcgis\desktop\desktop10.6\ArcToolbox\Toolboxes\Data Management Tools.tbx\CalculateField" Date="20230204" Time="230246">CalculateField 2019年\2019年县 备注 "2013年撤销陵县，设立陵城区" VB #</Process><Process ToolSource="e:\program files\arcgis\desktop\desktop10.6\ArcToolbox\Toolboxes\Data Management Tools.tbx\CalculateField" Date="20230204" Time="231425">CalculateField 2019年\2019年县 曾用名 "苍山县" VB #</Process><Process ToolSource="e:\program files\arcgis\desktop\desktop10.6\ArcToolbox\Toolboxes\Data Management Tools.tbx\CalculateField" Date="20230204" Time="231429">CalculateField 2019年\2019年县 备注 "2013年更名为兰陵县" VB #</Process><Process ToolSource="e:\program files\arcgis\desktop\desktop10.6\ArcToolbox\Toolboxes\Data Management Tools.tbx\CalculateField" Date="20230204" Time="232652">CalculateField 2019年\2019年县 曾用名 "双城市" VB #</Process><Process ToolSource="e:\program files\arcgis\desktop\desktop10.6\ArcToolbox\Toolboxes\Data Management Tools.tbx\CalculateField" Date="20230204" Time="232656">CalculateField 2019年\2019年县 备注 "2013年撤销双城市，设立双城区" VB #</Process><Process ToolSource="e:\program files\arcgis\desktop\desktop10.6\ArcToolbox\Toolboxes\Data Management Tools.tbx\CalculateField" Date="20230204" Time="233239">CalculateField 2019年\2019年县 曾用名 "赣榆县" VB #</Process><Process ToolSource="e:\program files\arcgis\desktop\desktop10.6\ArcToolbox\Toolboxes\Data Management Tools.tbx\CalculateField" Date="20230204" Time="233243">CalculateField 2019年\2019年县 备注 "2013年撤销赣榆县，设立赣榆区" VB #</Process><Process ToolSource="e:\program files\arcgis\desktop\desktop10.6\ArcToolbox\Toolboxes\Data Management Tools.tbx\CalculateField" Date="20230204" Time="235705">CalculateField 2019年\2019年县 曾用名 "建阳市" VB #</Process><Process ToolSource="e:\program files\arcgis\desktop\desktop10.6\ArcToolbox\Toolboxes\Data Management Tools.tbx\CalculateField" Date="20230204" Time="235709">CalculateField 2019年\2019年县 备注 "2013年撤销建阳市，设立建阳区" VB #</Process><Process ToolSource="e:\program files\arcgis\desktop\desktop10.6\ArcToolbox\Toolboxes\Data Management Tools.tbx\CalculateField" Date="20230205" Time="000346">CalculateField 2019年\2019年县 曾用名 "永定县" VB #</Process><Process ToolSource="e:\program files\arcgis\desktop\desktop10.6\ArcToolbox\Toolboxes\Data Management Tools.tbx\CalculateField" Date="20230205" Time="000350">CalculateField 2019年\2019年县 备注 "2013年撤销永定县，设立永定区" VB #</Process><Process ToolSource="e:\program files\arcgis\desktop\desktop10.6\ArcToolbox\Toolboxes\Data Management Tools.tbx\CalculateField" Date="20230207" Time="220018">CalculateField 2019年\2019年县 曾用名 "铜梁县" VB #</Process><Process ToolSource="e:\program files\arcgis\desktop\desktop10.6\ArcToolbox\Toolboxes\Data Management Tools.tbx\CalculateField" Date="20230207" Time="220022">CalculateField 2019年\2019年县 备注 "2013年撤销铜梁县，设立铜梁区" VB #</Process><Process ToolSource="e:\program files\arcgis\desktop\desktop10.6\ArcToolbox\Toolboxes\Data Management Tools.tbx\CalculateField" Date="20230207" Time="223207">CalculateField 2019年\2019年县 曾用名 "璧山县" VB #</Process><Process ToolSource="e:\program files\arcgis\desktop\desktop10.6\ArcToolbox\Toolboxes\Data Management Tools.tbx\CalculateField" Date="20230207" Time="223212">CalculateField 2019年\2019年县 备注 "2013年撤销璧山县，设立璧山区" VB #</Process><Process ToolSource="e:\program files\arcgis\desktop\desktop10.6\ArcToolbox\Toolboxes\Data Management Tools.tbx\CalculateField" Date="20230207" Time="224040">CalculateField 2019年\2019年县 曾用名 "郧县" VB #</Process><Process ToolSource="e:\program files\arcgis\desktop\desktop10.6\ArcToolbox\Toolboxes\Data Management Tools.tbx\CalculateField" Date="20230207" Time="224045">CalculateField 2019年\2019年县 备注 "2013年撤销郧县，设立郧阳区" VB #</Process><Process ToolSource="e:\program files\arcgis\desktop\desktop10.6\ArcToolbox\Toolboxes\Data Management Tools.tbx\CalculateField" Date="20230207" Time="224512">CalculateField 2019年\2019年县 曾用名 "开封县" VB #</Process><Process ToolSource="e:\program files\arcgis\desktop\desktop10.6\ArcToolbox\Toolboxes\Data Management Tools.tbx\CalculateField" Date="20230207" Time="224624">CalculateField 2019年\2019年县 备注 "2013年撤销开封县，设立祥符区" VB #</Process><Process ToolSource="e:\program files\arcgis\desktop\desktop10.6\ArcToolbox\Toolboxes\Data Management Tools.tbx\CalculateField" Date="20230207" Time="230655">CalculateField 2019年\2019年县 备注 "2013年撤销金明区，并入龙亭区" VB #</Process><Process ToolSource="e:\program files\arcgis\desktop\desktop10.6\ArcToolbox\Toolboxes\Data Management Tools.tbx\CalculateField" Date="20230207" Time="231358">CalculateField 2019年\2019年县 曾用名 "藁城市" VB #</Process><Process ToolSource="e:\program files\arcgis\desktop\desktop10.6\ArcToolbox\Toolboxes\Data Management Tools.tbx\CalculateField" Date="20230207" Time="231516">CalculateField 2019年\2019年县 备注 "2013年撤销藁城市，设立藁城区" VB #</Process><Process ToolSource="e:\program files\arcgis\desktop\desktop10.6\ArcToolbox\Toolboxes\Data Management Tools.tbx\CalculateField" Date="20230207" Time="232234">CalculateField 2019年\2019年县 曾用名 "鹿泉市" VB #</Process><Process ToolSource="e:\program files\arcgis\desktop\desktop10.6\ArcToolbox\Toolboxes\Data Management Tools.tbx\CalculateField" Date="20230207" Time="232346">CalculateField 2019年\2019年县 备注 "2013年撤销鹿泉市，设立鹿泉区" VB #</Process><Process ToolSource="e:\program files\arcgis\desktop\desktop10.6\ArcToolbox\Toolboxes\Data Management Tools.tbx\CalculateField" Date="20230207" Time="232631">CalculateField 2019年\2019年县 曾用名 "栾城县" VB #</Process><Process ToolSource="e:\program files\arcgis\desktop\desktop10.6\ArcToolbox\Toolboxes\Data Management Tools.tbx\CalculateField" Date="20230207" Time="232733">CalculateField 2019年\2019年县 备注 "2013年撤销栾城县，设立栾城区" VB #</Process><Process ToolSource="e:\program files\arcgis\desktop\desktop10.6\ArcToolbox\Toolboxes\Data Management Tools.tbx\CalculateField" Date="20230208" Time="000024">CalculateField 2019年\2019年县 曾用名 "彭山县" VB #</Process><Process ToolSource="e:\program files\arcgis\desktop\desktop10.6\ArcToolbox\Toolboxes\Data Management Tools.tbx\CalculateField" Date="20230208" Time="000136">CalculateField 2019年\2019年县 备注 "2013年撤销彭山县，设立彭山区" VB #</Process><Process ToolSource="e:\program files\arcgis\desktop\desktop10.6\ArcToolbox\Toolboxes\Data Management Tools.tbx\CalculateField" Date="20230208" Time="000721">CalculateField 2019年\2019年县 曾用名 "九台市" VB #</Process><Process ToolSource="e:\program files\arcgis\desktop\desktop10.6\ArcToolbox\Toolboxes\Data Management Tools.tbx\CalculateField" Date="20230208" Time="001010">CalculateField 2019年\2019年县 备注 "2013年撤销九台市，设立九台区" VB #</Process><Process ToolSource="e:\program files\arcgis\desktop\desktop10.6\ArcToolbox\Toolboxes\Data Management Tools.tbx\CalculateField" Date="20230208" Time="001458">CalculateField 2019年\2019年县 曾用名 "富阳市" VB #</Process><Process ToolSource="e:\program files\arcgis\desktop\desktop10.6\ArcToolbox\Toolboxes\Data Management Tools.tbx\CalculateField" Date="20230208" Time="001605">CalculateField 2019年\2019年县 备注 "2013年撤销富阳市，设立富阳区" VB #</Process><Process ToolSource="e:\program files\arcgis\desktop\desktop10.6\ArcToolbox\Toolboxes\Data Management Tools.tbx\CalculateField" Date="20230208" Time="002026">CalculateField 2019年\2019年县 曾用名 "高陵县" VB #</Process><Process ToolSource="e:\program files\arcgis\desktop\desktop10.6\ArcToolbox\Toolboxes\Data Management Tools.tbx\CalculateField" Date="20230208" Time="002231">CalculateField 2019年\2019年县 备注 "2013年撤销高陵县，设立高陵区" VB #</Process><Process ToolSource="e:\program files\arcgis\desktop\desktop10.6\ArcToolbox\Toolboxes\Data Management Tools.tbx\CalculateField" Date="20230208" Time="002730">CalculateField 2019年\2019年县 曾用名 "平坝县" VB #</Process><Process ToolSource="e:\program files\arcgis\desktop\desktop10.6\ArcToolbox\Toolboxes\Data Management Tools.tbx\CalculateField" Date="20230208" Time="002839">CalculateField 2019年\2019年县 备注 "2013年撤销平坝县，设立平坝区" VB #</Process><Process ToolSource="e:\program files\arcgis\desktop\desktop10.6\ArcToolbox\Toolboxes\Data Management Tools.tbx\CalculateField" Date="20230208" Time="235200">CalculateField 2019年\2019年县 曾用名 "日喀则市" VB #</Process><Process ToolSource="e:\program files\arcgis\desktop\desktop10.6\ArcToolbox\Toolboxes\Data Management Tools.tbx\CalculateField" Date="20230208" Time="235205">CalculateField 2019年\2019年县 备注 "2013年撤销日喀则市，设立桑珠孜区" VB #</Process><Process ToolSource="e:\program files\arcgis\desktop\desktop10.6\ArcToolbox\Toolboxes\Data Management Tools.tbx\CalculateField" Date="20230209" Time="002114">CalculateField 2019年\2019年县 备注 "2014年新设图木舒克市，省直管,是县级单位" VB #</Process><Process ToolSource="e:\program files\arcgis\desktop\desktop10.6\ArcToolbox\Toolboxes\Data Management Tools.tbx\CalculateField" Date="20230209" Time="002821">CalculateField 2019年\2019年县 备注 "2014年新设双河市，省直管,是县级单位" VB #</Process><Process ToolSource="e:\program files\arcgis\desktop\desktop10.6\ArcToolbox\Toolboxes\Data Management Tools.tbx\CalculateField" Date="20230209" Time="003244">CalculateField 2019年\2019年县 备注 "2014年新设霍尔果斯市" VB #</Process><Process ToolSource="e:\program files\arcgis\desktop\desktop10.6\ArcToolbox\Toolboxes\Data Management Tools.tbx\CalculateField" Date="20230209" Time="234012">CalculateField 2019年\2019年县 曾用名 "崖城镇" VB #</Process><Process ToolSource="e:\program files\arcgis\desktop\desktop10.6\ArcToolbox\Toolboxes\Data Management Tools.tbx\CalculateField" Date="20230209" Time="234222">CalculateField 2019年\2019年县 备注 "2014年撤销崖城镇，新设崖州区" VB #</Process><Process ToolSource="e:\program files\arcgis\desktop\desktop10.6\ArcToolbox\Toolboxes\Data Management Tools.tbx\CalculateField" Date="20230209" Time="234400">CalculateField 2019年\2019年县 备注 "2014年新设天涯区" VB #</Process><Process ToolSource="e:\program files\arcgis\desktop\desktop10.6\ArcToolbox\Toolboxes\Data Management Tools.tbx\CalculateField" Date="20230209" Time="234550">CalculateField 2019年\2019年县 曾用名 "吉阳镇" VB #</Process><Process ToolSource="e:\program files\arcgis\desktop\desktop10.6\ArcToolbox\Toolboxes\Data Management Tools.tbx\CalculateField" Date="20230209" Time="234654">CalculateField 2019年\2019年县 备注 "2014年撤销吉阳镇，新设吉阳区" VB #</Process><Process ToolSource="e:\program files\arcgis\desktop\desktop10.6\ArcToolbox\Toolboxes\Data Management Tools.tbx\CalculateField" Date="20230209" Time="234821">CalculateField 2019年\2019年县 曾用名 "海棠湾镇" VB #</Process><Process ToolSource="e:\program files\arcgis\desktop\desktop10.6\ArcToolbox\Toolboxes\Data Management Tools.tbx\CalculateField" Date="20230209" Time="234933">CalculateField 2019年\2019年县 备注 "2014年撤销海棠湾镇，新设海棠区 " VB #</Process><Process ToolSource="e:\program files\arcgis\desktop\desktop10.6\ArcToolbox\Toolboxes\Data Management Tools.tbx\CalculateField" Date="20230209" Time="235419">CalculateField 2019年\2019年县 曾用名 "东陵区 " VB #</Process><Process ToolSource="e:\program files\arcgis\desktop\desktop10.6\ArcToolbox\Toolboxes\Data Management Tools.tbx\CalculateField" Date="20230209" Time="235544">CalculateField 2019年\2019年县 备注 "2013年东陵区更名为浑南区" VB #</Process><Process ToolSource="e:\program files\arcgis\desktop\desktop10.6\ArcToolbox\Toolboxes\Data Management Tools.tbx\CalculateField" Date="20230209" Time="235630">CalculateField 2019年\2019年县 备注 "2014年东陵区更名为浑南区" VB #</Process><Process ToolSource="e:\program files\arcgis\desktop\desktop10.6\ArcToolbox\Toolboxes\Data Management Tools.tbx\CalculateField" Date="20230210" Time="000917">CalculateField 2019年\2019年县 曾用名 "香格里拉县" VB #</Process><Process ToolSource="e:\program files\arcgis\desktop\desktop10.6\ArcToolbox\Toolboxes\Data Management Tools.tbx\CalculateField" Date="20230210" Time="001116">CalculateField 2019年\2019年县 备注 "2013年撤销香格里拉县，设立香格里拉市" VB #</Process><Process ToolSource="e:\program files\arcgis\desktop\desktop10.6\ArcToolbox\Toolboxes\Data Management Tools.tbx\CalculateField" Date="20230212" Time="031206">CalculateField 2019年\2019年县 year 2019 VB #</Process><Process ToolSource="e:\program files\arcgis\desktop\desktop10.6\ArcToolbox\Toolboxes\Data Management Tools.tbx\CalculateField" Date="20230212" Time="173438">CalculateField 2019年\2019年县 曾用名 "昌都县" VB #</Process><Process ToolSource="e:\program files\arcgis\desktop\desktop10.6\ArcToolbox\Toolboxes\Data Management Tools.tbx\CalculateField" Date="20230212" Time="173443">CalculateField 2019年\2019年县 备注 "2014年撤销昌都县，设立卡若区" VB #</Process></lineage></DataProperties></Esri></metadata>
