<?xml version="1.0" encoding="UTF-8"?>
<metadata xml:lang="zh"><Esri><CreaDate>20230203</CreaDate><CreaTime>00490800</CreaTime><ArcGISFormat>1.0</ArcGISFormat><SyncOnce>TRUE</SyncOnce><DataProperties><lineage><Process ToolSource="c:\program files (x86)\arcgis\desktop10.6\ArcToolbox\Toolboxes\Data Management Tools.tbx\CalculateField" Date="20230131" Time="013238">CalculateField 2015年\2015年县级 year 2014 VB #</Process><Process ToolSource="e:\program files\arcgis\desktop\desktop10.6\ArcToolbox\Toolboxes\Data Management Tools.tbx\CalculateField" Date="20230204" Time="233418">CalculateField 2013年\2013年县 year 2013 VB #</Process><Process ToolSource="e:\program files\arcgis_pro_2.5\Resources\ArcToolbox\toolboxes\Data Management Tools.tbx\RepairGeometry" Date="20230212" Time="181125">RepairGeometry D:\博客\2013年行政区划数据\发布文件\2013年\2013年县\2013年县.shp DELETE_NULL Esri</Process><Process Name="修复几何" ToolSource="c:\program files\arcgis\pro\Resources\ArcToolbox\toolboxes\Data Management Tools.tbx\RepairGeometry" Date="20230925" Time="182352">RepairGeometry 2013年\2013年县 DELETE_NULL Esri</Process><Process Name="修复几何" ToolSource="c:\program files\arcgis\pro\Resources\ArcToolbox\toolboxes\Data Management Tools.tbx\RepairGeometry" Date="20230925" Time="182504">RepairGeometry 2013年\2013年县 DELETE_NULL OGC</Process><Process Name="修复几何" ToolSource="c:\program files\arcgis\pro\Resources\ArcToolbox\toolboxes\Data Management Tools.tbx\RepairGeometry" Date="20231013" Time="200305">RepairGeometry 2013年\2013年县 DELETE_NULL Esri</Process><Process Name="修复几何" ToolSource="c:\program files\arcgis\pro\Resources\ArcToolbox\toolboxes\Data Management Tools.tbx\RepairGeometry" Date="20231013" Time="200613">RepairGeometry 2013年\2013年县 DELETE_NULL OGC</Process><Process Name="修复几何" ToolSource="c:\program files\arcgis\pro\Resources\ArcToolbox\toolboxes\Data Management Tools.tbx\RepairGeometry" Date="20231015" Time="212948">RepairGeometry 2013年\2013年县 DELETE_NULL Esri</Process><Process Name="修复几何" ToolSource="c:\program files\arcgis\pro\Resources\ArcToolbox\toolboxes\Data Management Tools.tbx\RepairGeometry" Date="20231015" Time="213049">RepairGeometry 2013年\2013年县 DELETE_NULL OGC</Process></lineage></DataProperties></Esri></metadata>
